cnic3/1.py
cnic3/2.py
cnic3/3.py
cnic3/__init__.py
cnic3/csv_loader.py
cnic3/ipv6_init.py
cnic3/ipv6_pre.py
cnic3/train_data.py
cnic3-1.5.7.dist-info/METADATA
cnic3-1.5.7.dist-info/WHEEL
cnic3-1.5.7.dist-info/top_level.txt
cnic3-1.5.7.dist-info/RECORD
