Metadata-Version: 2.4
Name: cnic3
Version: 1.5.7
Summary: Advanced data loader and preprocessor for CSV and Parquet files
Author: cnic3
Classifier: Programming Language :: Python :: 3
Classifier: License :: OSI Approved :: MIT License
Requires-Python: >=3.7
Requires-Dist: pandas>=1.0
Dynamic: author
Dynamic: classifier
Dynamic: requires-dist
Dynamic: requires-python
Dynamic: summary
